{
  "runs": [
    {
      "id": "121420645",
      "timestamp": "2026-06-27T04:56:59Z",
      "ddprof_branch": "main",
      "ddprof_sha": "6680cf524b1c5af52aceda02de0bc29694af2641",
      "ddprof_pr": null,
      "pipeline": {
        "id": "121420645",
        "url": "https://gitlab.ddbuild.io/DataDog/java-profiler/-/pipelines/121420645"
      },
      "lib_version": "unknown",
      "status": "failed",
      "summary": {
        "total_jobs": 40,
        "passed_jobs": 0,
        "failed_jobs": 40,
        "total_scenarios": 80,
        "passed_scenarios": 0,
        "failed_scenarios": 0,
        "unknown_scenarios": 80,
        "failed_configs": [
          "glibc-arm64-hotspot-jdk11",
          "glibc-arm64-hotspot-jdk17",
          "glibc-arm64-hotspot-jdk21",
          "glibc-arm64-hotspot-jdk25",
          "glibc-arm64-hotspot-jdk8",
          "glibc-arm64-openj9-jdk11",
          "glibc-arm64-openj9-jdk17",
          "glibc-arm64-openj9-jdk21",
          "glibc-arm64-openj9-jdk25",
          "glibc-arm64-openj9-jdk8",
          "glibc-x64-hotspot-jdk11",
          "glibc-x64-hotspot-jdk17",
          "glibc-x64-hotspot-jdk21",
          "glibc-x64-hotspot-jdk25",
          "glibc-x64-hotspot-jdk8",
          "glibc-x64-openj9-jdk11",
          "glibc-x64-openj9-jdk17",
          "glibc-x64-openj9-jdk21",
          "glibc-x64-openj9-jdk25",
          "glibc-x64-openj9-jdk8",
          "musl-arm64-hotspot-jdk11",
          "musl-arm64-hotspot-jdk17",
          "musl-arm64-hotspot-jdk21",
          "musl-arm64-hotspot-jdk25",
          "musl-arm64-hotspot-jdk8",
          "musl-arm64-openj9-jdk11",
          "musl-arm64-openj9-jdk17",
          "musl-arm64-openj9-jdk21",
          "musl-arm64-openj9-jdk25",
          "musl-arm64-openj9-jdk8",
          "musl-x64-hotspot-jdk11",
          "musl-x64-hotspot-jdk17",
          "musl-x64-hotspot-jdk21",
          "musl-x64-hotspot-jdk25",
          "musl-x64-hotspot-jdk8",
          "musl-x64-openj9-jdk11",
          "musl-x64-openj9-jdk17",
          "musl-x64-openj9-jdk21",
          "musl-x64-openj9-jdk25",
          "musl-x64-openj9-jdk8"
        ]
      }
    },
    {
      "id": "121381849",
      "timestamp": "2026-06-26T20:37:36Z",
      "ddprof_branch": "main",
      "ddprof_sha": "bb3a19227489d8b70b88903a7e4d0a0b72e2b3b9",
      "ddprof_pr": null,
      "pipeline": {
        "id": "121381849",
        "url": "https://gitlab.ddbuild.io/DataDog/java-profiler/-/pipelines/121381849"
      },
      "lib_version": "unknown",
      "status": "failed",
      "summary": {
        "total_jobs": 40,
        "passed_jobs": 0,
        "failed_jobs": 40,
        "total_scenarios": 80,
        "passed_scenarios": 0,
        "failed_scenarios": 0,
        "unknown_scenarios": 80,
        "failed_configs": [
          "glibc-arm64-hotspot-jdk11",
          "glibc-arm64-hotspot-jdk17",
          "glibc-arm64-hotspot-jdk21",
          "glibc-arm64-hotspot-jdk25",
          "glibc-arm64-hotspot-jdk8",
          "glibc-arm64-openj9-jdk11",
          "glibc-arm64-openj9-jdk17",
          "glibc-arm64-openj9-jdk21",
          "glibc-arm64-openj9-jdk25",
          "glibc-arm64-openj9-jdk8",
          "glibc-x64-hotspot-jdk11",
          "glibc-x64-hotspot-jdk17",
          "glibc-x64-hotspot-jdk21",
          "glibc-x64-hotspot-jdk25",
          "glibc-x64-hotspot-jdk8",
          "glibc-x64-openj9-jdk11",
          "glibc-x64-openj9-jdk17",
          "glibc-x64-openj9-jdk21",
          "glibc-x64-openj9-jdk25",
          "glibc-x64-openj9-jdk8",
          "musl-arm64-hotspot-jdk11",
          "musl-arm64-hotspot-jdk17",
          "musl-arm64-hotspot-jdk21",
          "musl-arm64-hotspot-jdk25",
          "musl-arm64-hotspot-jdk8",
          "musl-arm64-openj9-jdk11",
          "musl-arm64-openj9-jdk17",
          "musl-arm64-openj9-jdk21",
          "musl-arm64-openj9-jdk25",
          "musl-arm64-openj9-jdk8",
          "musl-x64-hotspot-jdk11",
          "musl-x64-hotspot-jdk17",
          "musl-x64-hotspot-jdk21",
          "musl-x64-hotspot-jdk25",
          "musl-x64-hotspot-jdk8",
          "musl-x64-openj9-jdk11",
          "musl-x64-openj9-jdk17",
          "musl-x64-openj9-jdk21",
          "musl-x64-openj9-jdk25",
          "musl-x64-openj9-jdk8"
        ]
      }
    },
    {
      "id": "121379176",
      "timestamp": "2026-06-26T20:24:54Z",
      "ddprof_branch": "main",
      "ddprof_sha": "9bcf8fa5bee7a633caf0158f2c18e54637f06936",
      "ddprof_pr": null,
      "pipeline": {
        "id": "121379176",
        "url": "https://gitlab.ddbuild.io/DataDog/java-profiler/-/pipelines/121379176"
      },
      "lib_version": "unknown",
      "status": "failed",
      "summary": {
        "total_jobs": 40,
        "passed_jobs": 0,
        "failed_jobs": 40,
        "total_scenarios": 80,
        "passed_scenarios": 0,
        "failed_scenarios": 0,
        "unknown_scenarios": 80,
        "failed_configs": [
          "glibc-arm64-hotspot-jdk11",
          "glibc-arm64-hotspot-jdk17",
          "glibc-arm64-hotspot-jdk21",
          "glibc-arm64-hotspot-jdk25",
          "glibc-arm64-hotspot-jdk8",
          "glibc-arm64-openj9-jdk11",
          "glibc-arm64-openj9-jdk17",
          "glibc-arm64-openj9-jdk21",
          "glibc-arm64-openj9-jdk25",
          "glibc-arm64-openj9-jdk8",
          "glibc-x64-hotspot-jdk11",
          "glibc-x64-hotspot-jdk17",
          "glibc-x64-hotspot-jdk21",
          "glibc-x64-hotspot-jdk25",
          "glibc-x64-hotspot-jdk8",
          "glibc-x64-openj9-jdk11",
          "glibc-x64-openj9-jdk17",
          "glibc-x64-openj9-jdk21",
          "glibc-x64-openj9-jdk25",
          "glibc-x64-openj9-jdk8",
          "musl-arm64-hotspot-jdk11",
          "musl-arm64-hotspot-jdk17",
          "musl-arm64-hotspot-jdk21",
          "musl-arm64-hotspot-jdk25",
          "musl-arm64-hotspot-jdk8",
          "musl-arm64-openj9-jdk11",
          "musl-arm64-openj9-jdk17",
          "musl-arm64-openj9-jdk21",
          "musl-arm64-openj9-jdk25",
          "musl-arm64-openj9-jdk8",
          "musl-x64-hotspot-jdk11",
          "musl-x64-hotspot-jdk17",
          "musl-x64-hotspot-jdk21",
          "musl-x64-hotspot-jdk25",
          "musl-x64-hotspot-jdk8",
          "musl-x64-openj9-jdk11",
          "musl-x64-openj9-jdk17",
          "musl-x64-openj9-jdk21",
          "musl-x64-openj9-jdk25",
          "musl-x64-openj9-jdk8"
        ]
      }
    },
    {
      "id": "121366852",
      "timestamp": "2026-06-26T19:25:14Z",
      "ddprof_branch": "main",
      "ddprof_sha": "1b077afcaf74ccba4107625e828753775fcca7d0",
      "ddprof_pr": null,
      "pipeline": {
        "id": "121366852",
        "url": "https://gitlab.ddbuild.io/DataDog/java-profiler/-/pipelines/121366852"
      },
      "lib_version": "unknown",
      "status": "failed",
      "summary": {
        "total_jobs": 40,
        "passed_jobs": 0,
        "failed_jobs": 40,
        "total_scenarios": 80,
        "passed_scenarios": 0,
        "failed_scenarios": 0,
        "unknown_scenarios": 80,
        "failed_configs": [
          "glibc-arm64-hotspot-jdk11",
          "glibc-arm64-hotspot-jdk17",
          "glibc-arm64-hotspot-jdk21",
          "glibc-arm64-hotspot-jdk25",
          "glibc-arm64-hotspot-jdk8",
          "glibc-arm64-openj9-jdk11",
          "glibc-arm64-openj9-jdk17",
          "glibc-arm64-openj9-jdk21",
          "glibc-arm64-openj9-jdk25",
          "glibc-arm64-openj9-jdk8",
          "glibc-x64-hotspot-jdk11",
          "glibc-x64-hotspot-jdk17",
          "glibc-x64-hotspot-jdk21",
          "glibc-x64-hotspot-jdk25",
          "glibc-x64-hotspot-jdk8",
          "glibc-x64-openj9-jdk11",
          "glibc-x64-openj9-jdk17",
          "glibc-x64-openj9-jdk21",
          "glibc-x64-openj9-jdk25",
          "glibc-x64-openj9-jdk8",
          "musl-arm64-hotspot-jdk11",
          "musl-arm64-hotspot-jdk17",
          "musl-arm64-hotspot-jdk21",
          "musl-arm64-hotspot-jdk25",
          "musl-arm64-hotspot-jdk8",
          "musl-arm64-openj9-jdk11",
          "musl-arm64-openj9-jdk17",
          "musl-arm64-openj9-jdk21",
          "musl-arm64-openj9-jdk25",
          "musl-arm64-openj9-jdk8",
          "musl-x64-hotspot-jdk11",
          "musl-x64-hotspot-jdk17",
          "musl-x64-hotspot-jdk21",
          "musl-x64-hotspot-jdk25",
          "musl-x64-hotspot-jdk8",
          "musl-x64-openj9-jdk11",
          "musl-x64-openj9-jdk17",
          "musl-x64-openj9-jdk21",
          "musl-x64-openj9-jdk25",
          "musl-x64-openj9-jdk8"
        ]
      }
    },
    {
      "id": "121306917",
      "timestamp": "2026-06-26T15:16:27Z",
      "ddprof_branch": "main",
      "ddprof_sha": "ffd0b4688c1145429fadc71f5a099ea9ac5a8055",
      "ddprof_pr": null,
      "pipeline": {
        "id": "121306917",
        "url": "https://gitlab.ddbuild.io/DataDog/java-profiler/-/pipelines/121306917"
      },
      "lib_version": "unknown",
      "status": "failed",
      "summary": {
        "total_jobs": 40,
        "passed_jobs": 0,
        "failed_jobs": 40,
        "total_scenarios": 80,
        "passed_scenarios": 0,
        "failed_scenarios": 0,
        "unknown_scenarios": 80,
        "failed_configs": [
          "glibc-arm64-hotspot-jdk11",
          "glibc-arm64-hotspot-jdk17",
          "glibc-arm64-hotspot-jdk21",
          "glibc-arm64-hotspot-jdk25",
          "glibc-arm64-hotspot-jdk8",
          "glibc-arm64-openj9-jdk11",
          "glibc-arm64-openj9-jdk17",
          "glibc-arm64-openj9-jdk21",
          "glibc-arm64-openj9-jdk25",
          "glibc-arm64-openj9-jdk8",
          "glibc-x64-hotspot-jdk11",
          "glibc-x64-hotspot-jdk17",
          "glibc-x64-hotspot-jdk21",
          "glibc-x64-hotspot-jdk25",
          "glibc-x64-hotspot-jdk8",
          "glibc-x64-openj9-jdk11",
          "glibc-x64-openj9-jdk17",
          "glibc-x64-openj9-jdk21",
          "glibc-x64-openj9-jdk25",
          "glibc-x64-openj9-jdk8",
          "musl-arm64-hotspot-jdk11",
          "musl-arm64-hotspot-jdk17",
          "musl-arm64-hotspot-jdk21",
          "musl-arm64-hotspot-jdk25",
          "musl-arm64-hotspot-jdk8",
          "musl-arm64-openj9-jdk11",
          "musl-arm64-openj9-jdk17",
          "musl-arm64-openj9-jdk21",
          "musl-arm64-openj9-jdk25",
          "musl-arm64-openj9-jdk8",
          "musl-x64-hotspot-jdk11",
          "musl-x64-hotspot-jdk17",
          "musl-x64-hotspot-jdk21",
          "musl-x64-hotspot-jdk25",
          "musl-x64-hotspot-jdk8",
          "musl-x64-openj9-jdk11",
          "musl-x64-openj9-jdk17",
          "musl-x64-openj9-jdk21",
          "musl-x64-openj9-jdk25",
          "musl-x64-openj9-jdk8"
        ]
      }
    },
    {
      "id": "121303438",
      "timestamp": "2026-06-26T15:06:01Z",
      "ddprof_branch": "main",
      "ddprof_sha": "6680cf524b1c5af52aceda02de0bc29694af2641",
      "ddprof_pr": null,
      "pipeline": {
        "id": "121303438",
        "url": "https://gitlab.ddbuild.io/DataDog/java-profiler/-/pipelines/121303438"
      },
      "lib_version": "unknown",
      "status": "failed",
      "summary": {
        "total_jobs": 39,
        "passed_jobs": 0,
        "failed_jobs": 39,
        "total_scenarios": 78,
        "passed_scenarios": 0,
        "failed_scenarios": 0,
        "unknown_scenarios": 78,
        "failed_configs": [
          "glibc-arm64-hotspot-jdk11",
          "glibc-arm64-hotspot-jdk17",
          "glibc-arm64-hotspot-jdk21",
          "glibc-arm64-hotspot-jdk25",
          "glibc-arm64-hotspot-jdk8",
          "glibc-arm64-openj9-jdk11",
          "glibc-arm64-openj9-jdk17",
          "glibc-arm64-openj9-jdk21",
          "glibc-arm64-openj9-jdk25",
          "glibc-arm64-openj9-jdk8",
          "glibc-x64-hotspot-jdk11",
          "glibc-x64-hotspot-jdk17",
          "glibc-x64-hotspot-jdk21",
          "glibc-x64-hotspot-jdk25",
          "glibc-x64-hotspot-jdk8",
          "glibc-x64-openj9-jdk11",
          "glibc-x64-openj9-jdk17",
          "glibc-x64-openj9-jdk21",
          "glibc-x64-openj9-jdk25",
          "glibc-x64-openj9-jdk8",
          "musl-arm64-hotspot-jdk11",
          "musl-arm64-hotspot-jdk17",
          "musl-arm64-hotspot-jdk21",
          "musl-arm64-hotspot-jdk25",
          "musl-arm64-hotspot-jdk8",
          "musl-arm64-openj9-jdk11",
          "musl-arm64-openj9-jdk17",
          "musl-arm64-openj9-jdk21",
          "musl-arm64-openj9-jdk25",
          "musl-arm64-openj9-jdk8",
          "musl-x64-hotspot-jdk11",
          "musl-x64-hotspot-jdk17",
          "musl-x64-hotspot-jdk21",
          "musl-x64-hotspot-jdk25",
          "musl-x64-hotspot-jdk8",
          "musl-x64-openj9-jdk11",
          "musl-x64-openj9-jdk17",
          "musl-x64-openj9-jdk21",
          "musl-x64-openj9-jdk8"
        ]
      }
    },
    {
      "id": "121301381",
      "timestamp": "2026-06-26T14:54:00Z",
      "ddprof_branch": "main",
      "ddprof_sha": "c1ba65d1b28fbb92fe3de401b2b137c7a7c9f18d",
      "ddprof_pr": null,
      "pipeline": {
        "id": "121301381",
        "url": "https://gitlab.ddbuild.io/DataDog/java-profiler/-/pipelines/121301381"
      },
      "lib_version": "unknown",
      "status": "failed",
      "summary": {
        "total_jobs": 40,
        "passed_jobs": 0,
        "failed_jobs": 40,
        "total_scenarios": 80,
        "passed_scenarios": 0,
        "failed_scenarios": 0,
        "unknown_scenarios": 80,
        "failed_configs": [
          "glibc-arm64-hotspot-jdk11",
          "glibc-arm64-hotspot-jdk17",
          "glibc-arm64-hotspot-jdk21",
          "glibc-arm64-hotspot-jdk25",
          "glibc-arm64-hotspot-jdk8",
          "glibc-arm64-openj9-jdk11",
          "glibc-arm64-openj9-jdk17",
          "glibc-arm64-openj9-jdk21",
          "glibc-arm64-openj9-jdk25",
          "glibc-arm64-openj9-jdk8",
          "glibc-x64-hotspot-jdk11",
          "glibc-x64-hotspot-jdk17",
          "glibc-x64-hotspot-jdk21",
          "glibc-x64-hotspot-jdk25",
          "glibc-x64-hotspot-jdk8",
          "glibc-x64-openj9-jdk11",
          "glibc-x64-openj9-jdk17",
          "glibc-x64-openj9-jdk21",
          "glibc-x64-openj9-jdk25",
          "glibc-x64-openj9-jdk8",
          "musl-arm64-hotspot-jdk11",
          "musl-arm64-hotspot-jdk17",
          "musl-arm64-hotspot-jdk21",
          "musl-arm64-hotspot-jdk25",
          "musl-arm64-hotspot-jdk8",
          "musl-arm64-openj9-jdk11",
          "musl-arm64-openj9-jdk17",
          "musl-arm64-openj9-jdk21",
          "musl-arm64-openj9-jdk25",
          "musl-arm64-openj9-jdk8",
          "musl-x64-hotspot-jdk11",
          "musl-x64-hotspot-jdk17",
          "musl-x64-hotspot-jdk21",
          "musl-x64-hotspot-jdk25",
          "musl-x64-hotspot-jdk8",
          "musl-x64-openj9-jdk11",
          "musl-x64-openj9-jdk17",
          "musl-x64-openj9-jdk21",
          "musl-x64-openj9-jdk25",
          "musl-x64-openj9-jdk8"
        ]
      }
    },
    {
      "id": "121293067",
      "timestamp": "2026-06-26T14:25:03Z",
      "ddprof_branch": "main",
      "ddprof_sha": "b990fb305fc450f97b87b78a797ca6a847b7dac9",
      "ddprof_pr": null,
      "pipeline": {
        "id": "121293067",
        "url": "https://gitlab.ddbuild.io/DataDog/java-profiler/-/pipelines/121293067"
      },
      "lib_version": "unknown",
      "status": "failed",
      "summary": {
        "total_jobs": 40,
        "passed_jobs": 0,
        "failed_jobs": 40,
        "total_scenarios": 80,
        "passed_scenarios": 0,
        "failed_scenarios": 0,
        "unknown_scenarios": 80,
        "failed_configs": [
          "glibc-arm64-hotspot-jdk11",
          "glibc-arm64-hotspot-jdk17",
          "glibc-arm64-hotspot-jdk21",
          "glibc-arm64-hotspot-jdk25",
          "glibc-arm64-hotspot-jdk8",
          "glibc-arm64-openj9-jdk11",
          "glibc-arm64-openj9-jdk17",
          "glibc-arm64-openj9-jdk21",
          "glibc-arm64-openj9-jdk25",
          "glibc-arm64-openj9-jdk8",
          "glibc-x64-hotspot-jdk11",
          "glibc-x64-hotspot-jdk17",
          "glibc-x64-hotspot-jdk21",
          "glibc-x64-hotspot-jdk25",
          "glibc-x64-hotspot-jdk8",
          "glibc-x64-openj9-jdk11",
          "glibc-x64-openj9-jdk17",
          "glibc-x64-openj9-jdk21",
          "glibc-x64-openj9-jdk25",
          "glibc-x64-openj9-jdk8",
          "musl-arm64-hotspot-jdk11",
          "musl-arm64-hotspot-jdk17",
          "musl-arm64-hotspot-jdk21",
          "musl-arm64-hotspot-jdk25",
          "musl-arm64-hotspot-jdk8",
          "musl-arm64-openj9-jdk11",
          "musl-arm64-openj9-jdk17",
          "musl-arm64-openj9-jdk21",
          "musl-arm64-openj9-jdk25",
          "musl-arm64-openj9-jdk8",
          "musl-x64-hotspot-jdk11",
          "musl-x64-hotspot-jdk17",
          "musl-x64-hotspot-jdk21",
          "musl-x64-hotspot-jdk25",
          "musl-x64-hotspot-jdk8",
          "musl-x64-openj9-jdk11",
          "musl-x64-openj9-jdk17",
          "musl-x64-openj9-jdk21",
          "musl-x64-openj9-jdk25",
          "musl-x64-openj9-jdk8"
        ]
      }
    },
    {
      "id": "121288809",
      "timestamp": "2026-06-26T14:09:59Z",
      "ddprof_branch": "main",
      "ddprof_sha": "bb6c93bfae5cbdc00cc77d7fced84ae85735f8fd",
      "ddprof_pr": null,
      "pipeline": {
        "id": "121288809",
        "url": "https://gitlab.ddbuild.io/DataDog/java-profiler/-/pipelines/121288809"
      },
      "lib_version": "unknown",
      "status": "failed",
      "summary": {
        "total_jobs": 40,
        "passed_jobs": 0,
        "failed_jobs": 40,
        "total_scenarios": 80,
        "passed_scenarios": 0,
        "failed_scenarios": 0,
        "unknown_scenarios": 80,
        "failed_configs": [
          "glibc-arm64-hotspot-jdk11",
          "glibc-arm64-hotspot-jdk17",
          "glibc-arm64-hotspot-jdk21",
          "glibc-arm64-hotspot-jdk25",
          "glibc-arm64-hotspot-jdk8",
          "glibc-arm64-openj9-jdk11",
          "glibc-arm64-openj9-jdk17",
          "glibc-arm64-openj9-jdk21",
          "glibc-arm64-openj9-jdk25",
          "glibc-arm64-openj9-jdk8",
          "glibc-x64-hotspot-jdk11",
          "glibc-x64-hotspot-jdk17",
          "glibc-x64-hotspot-jdk21",
          "glibc-x64-hotspot-jdk25",
          "glibc-x64-hotspot-jdk8",
          "glibc-x64-openj9-jdk11",
          "glibc-x64-openj9-jdk17",
          "glibc-x64-openj9-jdk21",
          "glibc-x64-openj9-jdk25",
          "glibc-x64-openj9-jdk8",
          "musl-arm64-hotspot-jdk11",
          "musl-arm64-hotspot-jdk17",
          "musl-arm64-hotspot-jdk21",
          "musl-arm64-hotspot-jdk25",
          "musl-arm64-hotspot-jdk8",
          "musl-arm64-openj9-jdk11",
          "musl-arm64-openj9-jdk17",
          "musl-arm64-openj9-jdk21",
          "musl-arm64-openj9-jdk25",
          "musl-arm64-openj9-jdk8",
          "musl-x64-hotspot-jdk11",
          "musl-x64-hotspot-jdk17",
          "musl-x64-hotspot-jdk21",
          "musl-x64-hotspot-jdk25",
          "musl-x64-hotspot-jdk8",
          "musl-x64-openj9-jdk11",
          "musl-x64-openj9-jdk17",
          "musl-x64-openj9-jdk21",
          "musl-x64-openj9-jdk25",
          "musl-x64-openj9-jdk8"
        ]
      }
    },
    {
      "id": "121256816",
      "timestamp": "2026-06-26T12:02:11Z",
      "ddprof_branch": "main",
      "ddprof_sha": "36ce1bda9a980a048d98c29d63aab1683133649b",
      "ddprof_pr": null,
      "pipeline": {
        "id": "121256816",
        "url": "https://gitlab.ddbuild.io/DataDog/java-profiler/-/pipelines/121256816"
      },
      "lib_version": "unknown",
      "status": "failed",
      "summary": {
        "total_jobs": 40,
        "passed_jobs": 0,
        "failed_jobs": 40,
        "total_scenarios": 80,
        "passed_scenarios": 0,
        "failed_scenarios": 0,
        "unknown_scenarios": 80,
        "failed_configs": [
          "glibc-arm64-hotspot-jdk11",
          "glibc-arm64-hotspot-jdk17",
          "glibc-arm64-hotspot-jdk21",
          "glibc-arm64-hotspot-jdk25",
          "glibc-arm64-hotspot-jdk8",
          "glibc-arm64-openj9-jdk11",
          "glibc-arm64-openj9-jdk17",
          "glibc-arm64-openj9-jdk21",
          "glibc-arm64-openj9-jdk25",
          "glibc-arm64-openj9-jdk8",
          "glibc-x64-hotspot-jdk11",
          "glibc-x64-hotspot-jdk17",
          "glibc-x64-hotspot-jdk21",
          "glibc-x64-hotspot-jdk25",
          "glibc-x64-hotspot-jdk8",
          "glibc-x64-openj9-jdk11",
          "glibc-x64-openj9-jdk17",
          "glibc-x64-openj9-jdk21",
          "glibc-x64-openj9-jdk25",
          "glibc-x64-openj9-jdk8",
          "musl-arm64-hotspot-jdk11",
          "musl-arm64-hotspot-jdk17",
          "musl-arm64-hotspot-jdk21",
          "musl-arm64-hotspot-jdk25",
          "musl-arm64-hotspot-jdk8",
          "musl-arm64-openj9-jdk11",
          "musl-arm64-openj9-jdk17",
          "musl-arm64-openj9-jdk21",
          "musl-arm64-openj9-jdk25",
          "musl-arm64-openj9-jdk8",
          "musl-x64-hotspot-jdk11",
          "musl-x64-hotspot-jdk17",
          "musl-x64-hotspot-jdk21",
          "musl-x64-hotspot-jdk25",
          "musl-x64-hotspot-jdk8",
          "musl-x64-openj9-jdk11",
          "musl-x64-openj9-jdk17",
          "musl-x64-openj9-jdk21",
          "musl-x64-openj9-jdk25",
          "musl-x64-openj9-jdk8"
        ]
      }
    }
  ]
}
