{
  "runs": [
    {
      "id": "120000746",
      "timestamp": "2026-06-19T18:15:35Z",
      "ddprof_branch": "main",
      "ddprof_sha": "2d51776433add1266c0df20538268c160c33e5c2",
      "ddprof_pr": null,
      "pipeline": {
        "id": "120000746",
        "url": "https://gitlab.ddbuild.io/DataDog/java-profiler/-/pipelines/120000746"
      },
      "lib_version": "unknown",
      "status": "failed",
      "summary": {
        "total_jobs": 40,
        "passed_jobs": 0,
        "failed_jobs": 40,
        "total_scenarios": 80,
        "passed_scenarios": 0,
        "failed_scenarios": 0,
        "unknown_scenarios": 80,
        "failed_configs": [
          "glibc-arm64-hotspot-jdk11",
          "glibc-arm64-hotspot-jdk17",
          "glibc-arm64-hotspot-jdk21",
          "glibc-arm64-hotspot-jdk25",
          "glibc-arm64-hotspot-jdk8",
          "glibc-arm64-openj9-jdk11",
          "glibc-arm64-openj9-jdk17",
          "glibc-arm64-openj9-jdk21",
          "glibc-arm64-openj9-jdk25",
          "glibc-arm64-openj9-jdk8",
          "glibc-x64-hotspot-jdk11",
          "glibc-x64-hotspot-jdk17",
          "glibc-x64-hotspot-jdk21",
          "glibc-x64-hotspot-jdk25",
          "glibc-x64-hotspot-jdk8",
          "glibc-x64-openj9-jdk11",
          "glibc-x64-openj9-jdk17",
          "glibc-x64-openj9-jdk21",
          "glibc-x64-openj9-jdk25",
          "glibc-x64-openj9-jdk8",
          "musl-arm64-hotspot-jdk11",
          "musl-arm64-hotspot-jdk17",
          "musl-arm64-hotspot-jdk21",
          "musl-arm64-hotspot-jdk25",
          "musl-arm64-hotspot-jdk8",
          "musl-arm64-openj9-jdk11",
          "musl-arm64-openj9-jdk17",
          "musl-arm64-openj9-jdk21",
          "musl-arm64-openj9-jdk25",
          "musl-arm64-openj9-jdk8",
          "musl-x64-hotspot-jdk11",
          "musl-x64-hotspot-jdk17",
          "musl-x64-hotspot-jdk21",
          "musl-x64-hotspot-jdk25",
          "musl-x64-hotspot-jdk8",
          "musl-x64-openj9-jdk11",
          "musl-x64-openj9-jdk17",
          "musl-x64-openj9-jdk21",
          "musl-x64-openj9-jdk25",
          "musl-x64-openj9-jdk8"
        ]
      }
    },
    {
      "id": "119998017",
      "timestamp": "2026-06-19T17:47:40Z",
      "ddprof_branch": "main",
      "ddprof_sha": "05f1c4cdd20b422b0c539db74427355eb40b72c3",
      "ddprof_pr": null,
      "pipeline": {
        "id": "119998017",
        "url": "https://gitlab.ddbuild.io/DataDog/java-profiler/-/pipelines/119998017"
      },
      "lib_version": "unknown",
      "status": "failed",
      "summary": {
        "total_jobs": 40,
        "passed_jobs": 0,
        "failed_jobs": 40,
        "total_scenarios": 80,
        "passed_scenarios": 0,
        "failed_scenarios": 0,
        "unknown_scenarios": 80,
        "failed_configs": [
          "glibc-arm64-hotspot-jdk11",
          "glibc-arm64-hotspot-jdk17",
          "glibc-arm64-hotspot-jdk21",
          "glibc-arm64-hotspot-jdk25",
          "glibc-arm64-hotspot-jdk8",
          "glibc-arm64-openj9-jdk11",
          "glibc-arm64-openj9-jdk17",
          "glibc-arm64-openj9-jdk21",
          "glibc-arm64-openj9-jdk25",
          "glibc-arm64-openj9-jdk8",
          "glibc-x64-hotspot-jdk11",
          "glibc-x64-hotspot-jdk17",
          "glibc-x64-hotspot-jdk21",
          "glibc-x64-hotspot-jdk25",
          "glibc-x64-hotspot-jdk8",
          "glibc-x64-openj9-jdk11",
          "glibc-x64-openj9-jdk17",
          "glibc-x64-openj9-jdk21",
          "glibc-x64-openj9-jdk25",
          "glibc-x64-openj9-jdk8",
          "musl-arm64-hotspot-jdk11",
          "musl-arm64-hotspot-jdk17",
          "musl-arm64-hotspot-jdk21",
          "musl-arm64-hotspot-jdk25",
          "musl-arm64-hotspot-jdk8",
          "musl-arm64-openj9-jdk11",
          "musl-arm64-openj9-jdk17",
          "musl-arm64-openj9-jdk21",
          "musl-arm64-openj9-jdk25",
          "musl-arm64-openj9-jdk8",
          "musl-x64-hotspot-jdk11",
          "musl-x64-hotspot-jdk17",
          "musl-x64-hotspot-jdk21",
          "musl-x64-hotspot-jdk25",
          "musl-x64-hotspot-jdk8",
          "musl-x64-openj9-jdk11",
          "musl-x64-openj9-jdk17",
          "musl-x64-openj9-jdk21",
          "musl-x64-openj9-jdk25",
          "musl-x64-openj9-jdk8"
        ]
      }
    },
    {
      "id": "119989907",
      "timestamp": "2026-06-19T16:34:32Z",
      "ddprof_branch": "main",
      "ddprof_sha": "c8e0b58ed8f0245411a8a03ef941facd643c74ff",
      "ddprof_pr": null,
      "pipeline": {
        "id": "119989907",
        "url": "https://gitlab.ddbuild.io/DataDog/java-profiler/-/pipelines/119989907"
      },
      "lib_version": "unknown",
      "status": "failed",
      "summary": {
        "total_jobs": 40,
        "passed_jobs": 0,
        "failed_jobs": 40,
        "total_scenarios": 80,
        "passed_scenarios": 0,
        "failed_scenarios": 0,
        "unknown_scenarios": 80,
        "failed_configs": [
          "glibc-arm64-hotspot-jdk11",
          "glibc-arm64-hotspot-jdk17",
          "glibc-arm64-hotspot-jdk21",
          "glibc-arm64-hotspot-jdk25",
          "glibc-arm64-hotspot-jdk8",
          "glibc-arm64-openj9-jdk11",
          "glibc-arm64-openj9-jdk17",
          "glibc-arm64-openj9-jdk21",
          "glibc-arm64-openj9-jdk25",
          "glibc-arm64-openj9-jdk8",
          "glibc-x64-hotspot-jdk11",
          "glibc-x64-hotspot-jdk17",
          "glibc-x64-hotspot-jdk21",
          "glibc-x64-hotspot-jdk25",
          "glibc-x64-hotspot-jdk8",
          "glibc-x64-openj9-jdk11",
          "glibc-x64-openj9-jdk17",
          "glibc-x64-openj9-jdk21",
          "glibc-x64-openj9-jdk25",
          "glibc-x64-openj9-jdk8",
          "musl-arm64-hotspot-jdk11",
          "musl-arm64-hotspot-jdk17",
          "musl-arm64-hotspot-jdk21",
          "musl-arm64-hotspot-jdk25",
          "musl-arm64-hotspot-jdk8",
          "musl-arm64-openj9-jdk11",
          "musl-arm64-openj9-jdk17",
          "musl-arm64-openj9-jdk21",
          "musl-arm64-openj9-jdk25",
          "musl-arm64-openj9-jdk8",
          "musl-x64-hotspot-jdk11",
          "musl-x64-hotspot-jdk17",
          "musl-x64-hotspot-jdk21",
          "musl-x64-hotspot-jdk25",
          "musl-x64-hotspot-jdk8",
          "musl-x64-openj9-jdk11",
          "musl-x64-openj9-jdk17",
          "musl-x64-openj9-jdk21",
          "musl-x64-openj9-jdk25",
          "musl-x64-openj9-jdk8"
        ]
      }
    },
    {
      "id": "119978806",
      "timestamp": "2026-06-19T15:38:25Z",
      "ddprof_branch": "main",
      "ddprof_sha": "c8e0b58ed8f0245411a8a03ef941facd643c74ff",
      "ddprof_pr": null,
      "pipeline": {
        "id": "119978806",
        "url": "https://gitlab.ddbuild.io/DataDog/java-profiler/-/pipelines/119978806"
      },
      "lib_version": "unknown",
      "status": "failed",
      "summary": {
        "total_jobs": 40,
        "passed_jobs": 0,
        "failed_jobs": 40,
        "total_scenarios": 80,
        "passed_scenarios": 0,
        "failed_scenarios": 0,
        "unknown_scenarios": 80,
        "failed_configs": [
          "glibc-arm64-hotspot-jdk11",
          "glibc-arm64-hotspot-jdk17",
          "glibc-arm64-hotspot-jdk21",
          "glibc-arm64-hotspot-jdk25",
          "glibc-arm64-hotspot-jdk8",
          "glibc-arm64-openj9-jdk11",
          "glibc-arm64-openj9-jdk17",
          "glibc-arm64-openj9-jdk21",
          "glibc-arm64-openj9-jdk25",
          "glibc-arm64-openj9-jdk8",
          "glibc-x64-hotspot-jdk11",
          "glibc-x64-hotspot-jdk17",
          "glibc-x64-hotspot-jdk21",
          "glibc-x64-hotspot-jdk25",
          "glibc-x64-hotspot-jdk8",
          "glibc-x64-openj9-jdk11",
          "glibc-x64-openj9-jdk17",
          "glibc-x64-openj9-jdk21",
          "glibc-x64-openj9-jdk25",
          "glibc-x64-openj9-jdk8",
          "musl-arm64-hotspot-jdk11",
          "musl-arm64-hotspot-jdk17",
          "musl-arm64-hotspot-jdk21",
          "musl-arm64-hotspot-jdk25",
          "musl-arm64-hotspot-jdk8",
          "musl-arm64-openj9-jdk11",
          "musl-arm64-openj9-jdk17",
          "musl-arm64-openj9-jdk21",
          "musl-arm64-openj9-jdk25",
          "musl-arm64-openj9-jdk8",
          "musl-x64-hotspot-jdk11",
          "musl-x64-hotspot-jdk17",
          "musl-x64-hotspot-jdk21",
          "musl-x64-hotspot-jdk25",
          "musl-x64-hotspot-jdk8",
          "musl-x64-openj9-jdk11",
          "musl-x64-openj9-jdk17",
          "musl-x64-openj9-jdk21",
          "musl-x64-openj9-jdk25",
          "musl-x64-openj9-jdk8"
        ]
      }
    },
    {
      "id": "119968351",
      "timestamp": "2026-06-19T14:50:56Z",
      "ddprof_branch": "main",
      "ddprof_sha": "b64d1f1b4a8355d4a807d1a67582f7a118829739",
      "ddprof_pr": null,
      "pipeline": {
        "id": "119968351",
        "url": "https://gitlab.ddbuild.io/DataDog/java-profiler/-/pipelines/119968351"
      },
      "lib_version": "unknown",
      "status": "failed",
      "summary": {
        "total_jobs": 40,
        "passed_jobs": 0,
        "failed_jobs": 40,
        "total_scenarios": 80,
        "passed_scenarios": 0,
        "failed_scenarios": 0,
        "unknown_scenarios": 80,
        "failed_configs": [
          "glibc-arm64-hotspot-jdk11",
          "glibc-arm64-hotspot-jdk17",
          "glibc-arm64-hotspot-jdk21",
          "glibc-arm64-hotspot-jdk25",
          "glibc-arm64-hotspot-jdk8",
          "glibc-arm64-openj9-jdk11",
          "glibc-arm64-openj9-jdk17",
          "glibc-arm64-openj9-jdk21",
          "glibc-arm64-openj9-jdk25",
          "glibc-arm64-openj9-jdk8",
          "glibc-x64-hotspot-jdk11",
          "glibc-x64-hotspot-jdk17",
          "glibc-x64-hotspot-jdk21",
          "glibc-x64-hotspot-jdk25",
          "glibc-x64-hotspot-jdk8",
          "glibc-x64-openj9-jdk11",
          "glibc-x64-openj9-jdk17",
          "glibc-x64-openj9-jdk21",
          "glibc-x64-openj9-jdk25",
          "glibc-x64-openj9-jdk8",
          "musl-arm64-hotspot-jdk11",
          "musl-arm64-hotspot-jdk17",
          "musl-arm64-hotspot-jdk21",
          "musl-arm64-hotspot-jdk25",
          "musl-arm64-hotspot-jdk8",
          "musl-arm64-openj9-jdk11",
          "musl-arm64-openj9-jdk17",
          "musl-arm64-openj9-jdk21",
          "musl-arm64-openj9-jdk25",
          "musl-arm64-openj9-jdk8",
          "musl-x64-hotspot-jdk11",
          "musl-x64-hotspot-jdk17",
          "musl-x64-hotspot-jdk21",
          "musl-x64-hotspot-jdk25",
          "musl-x64-hotspot-jdk8",
          "musl-x64-openj9-jdk11",
          "musl-x64-openj9-jdk17",
          "musl-x64-openj9-jdk21",
          "musl-x64-openj9-jdk25",
          "musl-x64-openj9-jdk8"
        ]
      }
    },
    {
      "id": "119950918",
      "timestamp": "2026-06-19T13:49:33Z",
      "ddprof_branch": "main",
      "ddprof_sha": "321cf9d5ee12ac1077c39b7ff6085cd92840be9d",
      "ddprof_pr": null,
      "pipeline": {
        "id": "119950918",
        "url": "https://gitlab.ddbuild.io/DataDog/java-profiler/-/pipelines/119950918"
      },
      "lib_version": "unknown",
      "status": "failed",
      "summary": {
        "total_jobs": 40,
        "passed_jobs": 0,
        "failed_jobs": 40,
        "total_scenarios": 80,
        "passed_scenarios": 0,
        "failed_scenarios": 0,
        "unknown_scenarios": 80,
        "failed_configs": [
          "glibc-arm64-hotspot-jdk11",
          "glibc-arm64-hotspot-jdk17",
          "glibc-arm64-hotspot-jdk21",
          "glibc-arm64-hotspot-jdk25",
          "glibc-arm64-hotspot-jdk8",
          "glibc-arm64-openj9-jdk11",
          "glibc-arm64-openj9-jdk17",
          "glibc-arm64-openj9-jdk21",
          "glibc-arm64-openj9-jdk25",
          "glibc-arm64-openj9-jdk8",
          "glibc-x64-hotspot-jdk11",
          "glibc-x64-hotspot-jdk17",
          "glibc-x64-hotspot-jdk21",
          "glibc-x64-hotspot-jdk25",
          "glibc-x64-hotspot-jdk8",
          "glibc-x64-openj9-jdk11",
          "glibc-x64-openj9-jdk17",
          "glibc-x64-openj9-jdk21",
          "glibc-x64-openj9-jdk25",
          "glibc-x64-openj9-jdk8",
          "musl-arm64-hotspot-jdk11",
          "musl-arm64-hotspot-jdk17",
          "musl-arm64-hotspot-jdk21",
          "musl-arm64-hotspot-jdk25",
          "musl-arm64-hotspot-jdk8",
          "musl-arm64-openj9-jdk11",
          "musl-arm64-openj9-jdk17",
          "musl-arm64-openj9-jdk21",
          "musl-arm64-openj9-jdk25",
          "musl-arm64-openj9-jdk8",
          "musl-x64-hotspot-jdk11",
          "musl-x64-hotspot-jdk17",
          "musl-x64-hotspot-jdk21",
          "musl-x64-hotspot-jdk25",
          "musl-x64-hotspot-jdk8",
          "musl-x64-openj9-jdk11",
          "musl-x64-openj9-jdk17",
          "musl-x64-openj9-jdk21",
          "musl-x64-openj9-jdk25",
          "musl-x64-openj9-jdk8"
        ]
      }
    },
    {
      "id": "119950754",
      "timestamp": "2026-06-19T13:46:59Z",
      "ddprof_branch": "main",
      "ddprof_sha": "93362c8e5542913050b736e8f751e39936f4045b",
      "ddprof_pr": null,
      "pipeline": {
        "id": "119950754",
        "url": "https://gitlab.ddbuild.io/DataDog/java-profiler/-/pipelines/119950754"
      },
      "lib_version": "unknown",
      "status": "failed",
      "summary": {
        "total_jobs": 40,
        "passed_jobs": 0,
        "failed_jobs": 40,
        "total_scenarios": 80,
        "passed_scenarios": 0,
        "failed_scenarios": 0,
        "unknown_scenarios": 80,
        "failed_configs": [
          "glibc-arm64-hotspot-jdk11",
          "glibc-arm64-hotspot-jdk17",
          "glibc-arm64-hotspot-jdk21",
          "glibc-arm64-hotspot-jdk25",
          "glibc-arm64-hotspot-jdk8",
          "glibc-arm64-openj9-jdk11",
          "glibc-arm64-openj9-jdk17",
          "glibc-arm64-openj9-jdk21",
          "glibc-arm64-openj9-jdk25",
          "glibc-arm64-openj9-jdk8",
          "glibc-x64-hotspot-jdk11",
          "glibc-x64-hotspot-jdk17",
          "glibc-x64-hotspot-jdk21",
          "glibc-x64-hotspot-jdk25",
          "glibc-x64-hotspot-jdk8",
          "glibc-x64-openj9-jdk11",
          "glibc-x64-openj9-jdk17",
          "glibc-x64-openj9-jdk21",
          "glibc-x64-openj9-jdk25",
          "glibc-x64-openj9-jdk8",
          "musl-arm64-hotspot-jdk11",
          "musl-arm64-hotspot-jdk17",
          "musl-arm64-hotspot-jdk21",
          "musl-arm64-hotspot-jdk25",
          "musl-arm64-hotspot-jdk8",
          "musl-arm64-openj9-jdk11",
          "musl-arm64-openj9-jdk17",
          "musl-arm64-openj9-jdk21",
          "musl-arm64-openj9-jdk25",
          "musl-arm64-openj9-jdk8",
          "musl-x64-hotspot-jdk11",
          "musl-x64-hotspot-jdk17",
          "musl-x64-hotspot-jdk21",
          "musl-x64-hotspot-jdk25",
          "musl-x64-hotspot-jdk8",
          "musl-x64-openj9-jdk11",
          "musl-x64-openj9-jdk17",
          "musl-x64-openj9-jdk21",
          "musl-x64-openj9-jdk25",
          "musl-x64-openj9-jdk8"
        ]
      }
    },
    {
      "id": "119914248",
      "timestamp": "2026-06-19T10:46:56Z",
      "ddprof_branch": "main",
      "ddprof_sha": "90c80bd434e80677895681b22efa1c7faa637e53",
      "ddprof_pr": null,
      "pipeline": {
        "id": "119914248",
        "url": "https://gitlab.ddbuild.io/DataDog/java-profiler/-/pipelines/119914248"
      },
      "lib_version": "unknown",
      "status": "failed",
      "summary": {
        "total_jobs": 40,
        "passed_jobs": 0,
        "failed_jobs": 40,
        "total_scenarios": 80,
        "passed_scenarios": 0,
        "failed_scenarios": 0,
        "unknown_scenarios": 80,
        "failed_configs": [
          "glibc-arm64-hotspot-jdk11",
          "glibc-arm64-hotspot-jdk17",
          "glibc-arm64-hotspot-jdk21",
          "glibc-arm64-hotspot-jdk25",
          "glibc-arm64-hotspot-jdk8",
          "glibc-arm64-openj9-jdk11",
          "glibc-arm64-openj9-jdk17",
          "glibc-arm64-openj9-jdk21",
          "glibc-arm64-openj9-jdk25",
          "glibc-arm64-openj9-jdk8",
          "glibc-x64-hotspot-jdk11",
          "glibc-x64-hotspot-jdk17",
          "glibc-x64-hotspot-jdk21",
          "glibc-x64-hotspot-jdk25",
          "glibc-x64-hotspot-jdk8",
          "glibc-x64-openj9-jdk11",
          "glibc-x64-openj9-jdk17",
          "glibc-x64-openj9-jdk21",
          "glibc-x64-openj9-jdk25",
          "glibc-x64-openj9-jdk8",
          "musl-arm64-hotspot-jdk11",
          "musl-arm64-hotspot-jdk17",
          "musl-arm64-hotspot-jdk21",
          "musl-arm64-hotspot-jdk25",
          "musl-arm64-hotspot-jdk8",
          "musl-arm64-openj9-jdk11",
          "musl-arm64-openj9-jdk17",
          "musl-arm64-openj9-jdk21",
          "musl-arm64-openj9-jdk25",
          "musl-arm64-openj9-jdk8",
          "musl-x64-hotspot-jdk11",
          "musl-x64-hotspot-jdk17",
          "musl-x64-hotspot-jdk21",
          "musl-x64-hotspot-jdk25",
          "musl-x64-hotspot-jdk8",
          "musl-x64-openj9-jdk11",
          "musl-x64-openj9-jdk17",
          "musl-x64-openj9-jdk21",
          "musl-x64-openj9-jdk25",
          "musl-x64-openj9-jdk8"
        ]
      }
    },
    {
      "id": "119911853",
      "timestamp": "2026-06-19T10:25:37Z",
      "ddprof_branch": "main",
      "ddprof_sha": "893f2fab66b860de55acf019b1c971bcbb58d66a",
      "ddprof_pr": null,
      "pipeline": {
        "id": "119911853",
        "url": "https://gitlab.ddbuild.io/DataDog/java-profiler/-/pipelines/119911853"
      },
      "lib_version": "unknown",
      "status": "failed",
      "summary": {
        "total_jobs": 40,
        "passed_jobs": 0,
        "failed_jobs": 40,
        "total_scenarios": 80,
        "passed_scenarios": 0,
        "failed_scenarios": 0,
        "unknown_scenarios": 80,
        "failed_configs": [
          "glibc-arm64-hotspot-jdk11",
          "glibc-arm64-hotspot-jdk17",
          "glibc-arm64-hotspot-jdk21",
          "glibc-arm64-hotspot-jdk25",
          "glibc-arm64-hotspot-jdk8",
          "glibc-arm64-openj9-jdk11",
          "glibc-arm64-openj9-jdk17",
          "glibc-arm64-openj9-jdk21",
          "glibc-arm64-openj9-jdk25",
          "glibc-arm64-openj9-jdk8",
          "glibc-x64-hotspot-jdk11",
          "glibc-x64-hotspot-jdk17",
          "glibc-x64-hotspot-jdk21",
          "glibc-x64-hotspot-jdk25",
          "glibc-x64-hotspot-jdk8",
          "glibc-x64-openj9-jdk11",
          "glibc-x64-openj9-jdk17",
          "glibc-x64-openj9-jdk21",
          "glibc-x64-openj9-jdk25",
          "glibc-x64-openj9-jdk8",
          "musl-arm64-hotspot-jdk11",
          "musl-arm64-hotspot-jdk17",
          "musl-arm64-hotspot-jdk21",
          "musl-arm64-hotspot-jdk25",
          "musl-arm64-hotspot-jdk8",
          "musl-arm64-openj9-jdk11",
          "musl-arm64-openj9-jdk17",
          "musl-arm64-openj9-jdk21",
          "musl-arm64-openj9-jdk25",
          "musl-arm64-openj9-jdk8",
          "musl-x64-hotspot-jdk11",
          "musl-x64-hotspot-jdk17",
          "musl-x64-hotspot-jdk21",
          "musl-x64-hotspot-jdk25",
          "musl-x64-hotspot-jdk8",
          "musl-x64-openj9-jdk11",
          "musl-x64-openj9-jdk17",
          "musl-x64-openj9-jdk21",
          "musl-x64-openj9-jdk25",
          "musl-x64-openj9-jdk8"
        ]
      }
    },
    {
      "id": "119903907",
      "timestamp": "2026-06-19T09:50:08Z",
      "ddprof_branch": "main",
      "ddprof_sha": "48d5522bcbd619b3fcb115bae49e72b69fdf9e07",
      "ddprof_pr": null,
      "pipeline": {
        "id": "119903907",
        "url": "https://gitlab.ddbuild.io/DataDog/java-profiler/-/pipelines/119903907"
      },
      "lib_version": "unknown",
      "status": "failed",
      "summary": {
        "total_jobs": 40,
        "passed_jobs": 0,
        "failed_jobs": 40,
        "total_scenarios": 80,
        "passed_scenarios": 0,
        "failed_scenarios": 0,
        "unknown_scenarios": 80,
        "failed_configs": [
          "glibc-arm64-hotspot-jdk11",
          "glibc-arm64-hotspot-jdk17",
          "glibc-arm64-hotspot-jdk21",
          "glibc-arm64-hotspot-jdk25",
          "glibc-arm64-hotspot-jdk8",
          "glibc-arm64-openj9-jdk11",
          "glibc-arm64-openj9-jdk17",
          "glibc-arm64-openj9-jdk21",
          "glibc-arm64-openj9-jdk25",
          "glibc-arm64-openj9-jdk8",
          "glibc-x64-hotspot-jdk11",
          "glibc-x64-hotspot-jdk17",
          "glibc-x64-hotspot-jdk21",
          "glibc-x64-hotspot-jdk25",
          "glibc-x64-hotspot-jdk8",
          "glibc-x64-openj9-jdk11",
          "glibc-x64-openj9-jdk17",
          "glibc-x64-openj9-jdk21",
          "glibc-x64-openj9-jdk25",
          "glibc-x64-openj9-jdk8",
          "musl-arm64-hotspot-jdk11",
          "musl-arm64-hotspot-jdk17",
          "musl-arm64-hotspot-jdk21",
          "musl-arm64-hotspot-jdk25",
          "musl-arm64-hotspot-jdk8",
          "musl-arm64-openj9-jdk11",
          "musl-arm64-openj9-jdk17",
          "musl-arm64-openj9-jdk21",
          "musl-arm64-openj9-jdk25",
          "musl-arm64-openj9-jdk8",
          "musl-x64-hotspot-jdk11",
          "musl-x64-hotspot-jdk17",
          "musl-x64-hotspot-jdk21",
          "musl-x64-hotspot-jdk25",
          "musl-x64-hotspot-jdk8",
          "musl-x64-openj9-jdk11",
          "musl-x64-openj9-jdk17",
          "musl-x64-openj9-jdk21",
          "musl-x64-openj9-jdk25",
          "musl-x64-openj9-jdk8"
        ]
      }
    }
  ]
}
