{
  "runs": [
    {
      "id": "107656844",
      "timestamp": "2026-04-14T17:30:49Z",
      "ddprof_branch": "main",
      "ddprof_sha": "unknown",
      "ddprof_pr": null,
      "pipeline": {
        "id": "107656844",
        "url": "https://gitlab.ddbuild.io/DataDog/java-profiler/-/pipelines/107656844"
      },
      "lib_version": "unknown",
      "status": "unknown",
      "summary": {
        "total_jobs": 0,
        "passed_jobs": 0,
        "failed_jobs": 0,
        "total_scenarios": 0,
        "passed_scenarios": 0,
        "failed_scenarios": 0,
        "unknown_scenarios": 0,
        "failed_configs": []
      }
    },
    {
      "id": "107618546",
      "timestamp": "2026-04-14T15:42:09Z",
      "ddprof_branch": "main",
      "ddprof_sha": "0a429fdf2d99897ae9be4b8a308428e7f488efd1",
      "ddprof_pr": null,
      "pipeline": {
        "id": "107618546",
        "url": "https://gitlab.ddbuild.io/DataDog/java-profiler/-/pipelines/107618546"
      },
      "lib_version": "unknown",
      "status": "passed",
      "summary": {
        "total_jobs": 40,
        "passed_jobs": 40,
        "failed_jobs": 0,
        "total_scenarios": 80,
        "passed_scenarios": 80,
        "failed_scenarios": 0,
        "unknown_scenarios": 0,
        "failed_configs": []
      }
    },
    {
      "id": "107582273",
      "timestamp": "2026-04-14T13:37:36Z",
      "ddprof_branch": "main",
      "ddprof_sha": "unknown",
      "ddprof_pr": null,
      "pipeline": {
        "id": "107582273",
        "url": "https://gitlab.ddbuild.io/DataDog/java-profiler/-/pipelines/107582273"
      },
      "lib_version": "unknown",
      "status": "unknown",
      "summary": {
        "total_jobs": 0,
        "passed_jobs": 0,
        "failed_jobs": 0,
        "total_scenarios": 0,
        "passed_scenarios": 0,
        "failed_scenarios": 0,
        "unknown_scenarios": 0,
        "failed_configs": []
      }
    },
    {
      "id": "107570548",
      "timestamp": "2026-04-14T13:05:32Z",
      "ddprof_branch": "main",
      "ddprof_sha": "344b89d2bd817ccb52dcc572e3f18517b10095a6",
      "ddprof_pr": null,
      "pipeline": {
        "id": "107570548",
        "url": "https://gitlab.ddbuild.io/DataDog/java-profiler/-/pipelines/107570548"
      },
      "lib_version": "unknown",
      "status": "passed",
      "summary": {
        "total_jobs": 40,
        "passed_jobs": 40,
        "failed_jobs": 0,
        "total_scenarios": 80,
        "passed_scenarios": 80,
        "failed_scenarios": 0,
        "unknown_scenarios": 0,
        "failed_configs": []
      }
    },
    {
      "id": "107559285",
      "timestamp": "2026-04-14T11:59:58Z",
      "ddprof_branch": "main",
      "ddprof_sha": "662cb1c3bae67d2544af6fb86da4f4be83f16a29",
      "ddprof_pr": null,
      "pipeline": {
        "id": "107559285",
        "url": "https://gitlab.ddbuild.io/DataDog/java-profiler/-/pipelines/107559285"
      },
      "lib_version": "unknown",
      "status": "partial",
      "summary": {
        "total_jobs": 40,
        "passed_jobs": 39,
        "failed_jobs": 1,
        "total_scenarios": 79,
        "passed_scenarios": 79,
        "failed_scenarios": 0,
        "unknown_scenarios": 0,
        "failed_configs": [
          "musl-arm64-openj9-jdk8"
        ]
      }
    },
    {
      "id": "107542668",
      "timestamp": "2026-04-14T10:19:11Z",
      "ddprof_branch": "main",
      "ddprof_sha": "3c4a56a8dc9e9000b070d4d24e46783cfdaf2f65",
      "ddprof_pr": null,
      "pipeline": {
        "id": "107542668",
        "url": "https://gitlab.ddbuild.io/DataDog/java-profiler/-/pipelines/107542668"
      },
      "lib_version": "unknown",
      "status": "passed",
      "summary": {
        "total_jobs": 40,
        "passed_jobs": 40,
        "failed_jobs": 0,
        "total_scenarios": 80,
        "passed_scenarios": 80,
        "failed_scenarios": 0,
        "unknown_scenarios": 0,
        "failed_configs": []
      }
    },
    {
      "id": "107527764",
      "timestamp": "2026-04-14T08:48:42Z",
      "ddprof_branch": "main",
      "ddprof_sha": "11b9b836ad4a8de2519c200ed7856a0e476a04ba",
      "ddprof_pr": null,
      "pipeline": {
        "id": "107527764",
        "url": "https://gitlab.ddbuild.io/DataDog/java-profiler/-/pipelines/107527764"
      },
      "lib_version": "unknown",
      "status": "passed",
      "summary": {
        "total_jobs": 40,
        "passed_jobs": 40,
        "failed_jobs": 0,
        "total_scenarios": 80,
        "passed_scenarios": 80,
        "failed_scenarios": 0,
        "unknown_scenarios": 0,
        "failed_configs": []
      }
    },
    {
      "id": "107527698",
      "timestamp": "2026-04-14T08:48:33Z",
      "ddprof_branch": "main",
      "ddprof_sha": "6c1be8669d4266a2b065c2cb61fb22ac810ca96d",
      "ddprof_pr": null,
      "pipeline": {
        "id": "107527698",
        "url": "https://gitlab.ddbuild.io/DataDog/java-profiler/-/pipelines/107527698"
      },
      "lib_version": "unknown",
      "status": "passed",
      "summary": {
        "total_jobs": 40,
        "passed_jobs": 40,
        "failed_jobs": 0,
        "total_scenarios": 80,
        "passed_scenarios": 80,
        "failed_scenarios": 0,
        "unknown_scenarios": 0,
        "failed_configs": []
      }
    },
    {
      "id": "107527707",
      "timestamp": "2026-04-14T08:46:40Z",
      "ddprof_branch": "main",
      "ddprof_sha": "daa6d4a89fb3999570586eafacbbb795300401ee",
      "ddprof_pr": null,
      "pipeline": {
        "id": "107527707",
        "url": "https://gitlab.ddbuild.io/DataDog/java-profiler/-/pipelines/107527707"
      },
      "lib_version": "unknown",
      "status": "passed",
      "summary": {
        "total_jobs": 40,
        "passed_jobs": 40,
        "failed_jobs": 0,
        "total_scenarios": 80,
        "passed_scenarios": 80,
        "failed_scenarios": 0,
        "unknown_scenarios": 0,
        "failed_configs": []
      }
    },
    {
      "id": "107401919",
      "timestamp": "2026-04-13T15:55:54Z",
      "ddprof_branch": "main",
      "ddprof_sha": "fda2a5b8e40792d31cdfd71dd6c57593fcde7fee",
      "ddprof_pr": null,
      "pipeline": {
        "id": "107401919",
        "url": "https://gitlab.ddbuild.io/DataDog/java-profiler/-/pipelines/107401919"
      },
      "lib_version": "unknown",
      "status": "passed",
      "summary": {
        "total_jobs": 40,
        "passed_jobs": 40,
        "failed_jobs": 0,
        "total_scenarios": 80,
        "passed_scenarios": 80,
        "failed_scenarios": 0,
        "unknown_scenarios": 0,
        "failed_configs": []
      }
    }
  ]
}
